{"data": [{"option_id": "1466", "option_type": "1", "option_name": "全局选项", "multi_select": 1, "option_data": [{"id": "8054", "title": "世界答题"}, {"id": "8056", "title": "组3人开始"}, {"id": "8058", "title": "一键喊话"}, {"id": "8060", "title": "点击需求"}, {"id": "15714", "title": "切换角色"}]}, {"option_id": "1468", "option_type": "2", "option_name": "匹配等级", "multi_select": 0, "option_data": [{"id": "8378", "title": "匹配10级内"}, {"id": "8064", "title": "匹配5级内"}, {"id": "8066", "title": "带新人"}]}, {"option_id": "1470", "option_type": "1", "option_name": "选择一条龙任务", "multi_select": 1, "option_data": [{"id": "8068", "title": "剧情副本"}, {"id": "8070", "title": "乱世妖魔"}, {"id": "8072", "title": "镇妖"}]}, {"option_id": "1472", "option_type": "5", "option_name": "剧情副本", "option_category": [{"option_id": "1472", "name": "普通难度", "multi_select": "1", "option_data": [{"id": "8076", "title": "黑石问情", "variable": "pthswq"}, {"id": "8078", "title": "古窟惊魂", "variable": "ptgkjh"}, {"id": "8080", "title": "修罗浩劫", "variable": "ptxlhj"}]}, {"option_id": "1472", "name": "精英难度", "multi_select": "1", "option_data": [{"id": "8082", "title": "黑石问情", "variable": "jyhswq"}, {"id": "8084", "title": "古窟惊魂", "variable": "jygkjh"}, {"id": "8086", "title": "修罗浩劫", "variable": "jyxlhj"}]}, {"option_id": "1472", "name": "英雄难度", "multi_select": "1", "option_data": [{"id": "8090", "title": "正魔大战", "variable": "yxzmdz"}, {"id": "8088", "title": "兽神灭世", "variable": "yxssms"}]}]}, {"option_id": "1474", "option_type": "5", "option_name": "镇妖", "option_category": [{"option_id": "1474", "name": "领双选择", "multi_select": "0", "option_data": [{"id": "8092", "title": "全程领双", "variable": "cd"}, {"id": "8094", "title": "第五次领双", "variable": "cd"}, {"id": "8096", "title": "第六次领双", "variable": "cd"}, {"id": "8098", "title": "第七次领双", "variable": "cd"}]}]}], "tops": ""}