{"data": [{"option_id": "2500", "option_type": "1", "option_name": "挂机设置", "multi_select": 1, "option_data": [{"id": "15606", "title": "关闭补充食品"}, {"id": "15700", "title": "零点领奖"}, {"id": "15732", "title": "清理背包"}, {"id": "16230", "title": "分解装备（白，蓝）"}, {"id": "16807", "title": "原地等待"}]}, {"option_id": "2382", "option_type": "2", "option_name": "设置怪物", "multi_select": 0, "option_data": [{"id": "14906", "title": "蟠龙旅-士兵枯骨(48级)"}, {"id": "14908", "title": "蟠龙旅-无名箭手(42级)"}, {"id": "14910", "title": "蟠龙旅-无脑残躯(50级)"}, {"id": "14912", "title": "蟠龙旅-海贼枯骨(55级)"}, {"id": "14914", "title": "中州商会-地鬼(54级)"}, {"id": "14916", "title": "中州商会-野人战士(54级)"}, {"id": "14918", "title": "中州商会-凶暴地源兽(53级)"}, {"id": "14920", "title": "中州商会-横行蟹(49级)"}, {"id": "14922", "title": "建木之民-荆蝎(58级)"}, {"id": "14924", "title": "建木之民-仙人刺球(58级)"}, {"id": "14926", "title": "建木之民-长蛮探子(58级)"}, {"id": "14928", "title": "建木之民-嚎啕蛊(58级)"}]}, {"option_id": "2448", "option_type": "2", "option_name": "设置队伍", "multi_select": 0, "option_data": [{"id": "15278", "title": "带队（队伍）"}, {"id": "15280", "title": "跟队（团队）"}]}, {"option_id": "2406", "option_type": "1", "option_name": "限时任务", "multi_select": 1, "option_data": [{"id": "15000", "title": "逸灵山谷争夺战"}, {"id": "15488", "title": "逐灭恶灵"}, {"id": "15490", "title": "决战修仙帮"}, {"id": "15492", "title": "修仙帮长老"}, {"id": "15494", "title": "每日答题"}, {"id": "15496", "title": "科举答题"}, {"id": "15498", "title": "科举终试"}, {"id": "15576", "title": "帮派联赛"}, {"id": "15578", "title": "仙魔劫"}, {"id": "15580", "title": "格斗场"}, {"id": "15712", "title": "熊万军的春天"}, {"id": "15792", "title": "帮派神兽"}, {"id": "15794", "title": "修罗道"}]}, {"option_id": "2486", "option_type": "5", "option_name": "五行之序", "option_category": [{"option_id": "2486", "name": "设置", "multi_select": "0", "option_data": [{"id": "15480", "title": "1-3阶", "variable": "wxzx"}, {"id": "15482", "title": "4-6阶", "variable": "wxzx"}, {"id": "15484", "title": "7-9阶", "variable": "wxzx"}, {"id": "15486", "title": "10-12阶", "variable": "wxzx"}, {"id": "17193", "title": "13-15阶", "variable": "wxzx"}, {"id": "17195", "title": "16-18阶", "variable": "wxzx"}]}]}, {"option_id": "2640", "option_type": "5", "option_name": "自动补血（左槽）", "option_category": [{"option_id": "2640", "name": "设置血量百分比", "multi_select": "0", "option_data": [{"id": "16248", "title": "30%", "variable": "hong"}, {"id": "16250", "title": "50%", "variable": "hong"}, {"id": "16252", "title": "70%", "variable": "hong"}]}]}, {"option_id": "2642", "option_type": "5", "option_name": "自动补蓝（右槽）", "option_category": [{"option_id": "2642", "name": "设置蓝量百分比", "multi_select": "0", "option_data": [{"id": "16254", "title": "30%", "variable": "lan"}, {"id": "16256", "title": "50%", "variable": "lan"}, {"id": "16258", "title": "70%", "variable": "lan"}]}]}], "tops": ""}